mapioulib/__init__.py
mapioulib/mapiou.py
mapioulib/matching.py
mapioulib/segment.py
mapioulib/video.py
mapioulib-0.2.0.dist-info/METADATA
mapioulib-0.2.0.dist-info/WHEEL
mapioulib-0.2.0.dist-info/top_level.txt
mapioulib-0.2.0.dist-info/RECORD
